__init__.py
__main__.py
beginnings.py
log.py
y.py
yh.py
yz.py
a_3y-2.6.4.dist-info/LICENCE.txt
a_3y-2.6.4.dist-info/METADATA
a_3y-2.6.4.dist-info/WHEEL
a_3y-2.6.4.dist-info/top_level.txt
a_3y-2.6.4.dist-info/zip-safe
a_3y-2.6.4.dist-info/RECORD
