Metadata-Version: 2.1
Name: a-3y
Version: 2.6.4
Summary: 三圆计算器,cmd或命令行 python 3y 命令开始运行
Home-page: UNKNOWN
Author: 神秘的·
Author-email: 3046479366@qq.com
License: MIT
Keywords: 3y
Platform: UNKNOWN
Classifier: License :: OSI Approved :: MIT License
Classifier: Programming Language :: Python :: 3
Classifier: Intended Audience :: Developers
Classifier: Operating System :: OS Independent
License-File: LICENCE.txt
Requires-Dist: pdsystem
Requires-Dist: beginnings
